setup.py
client/__init__.py
client/client.py
client/client/__init__.py
client/client/add_contact.py
client/client/database.py
client/client/del_contact.py
client/client/main_window.py
client/client/main_window_conv.py
client/client/start_dialog.py
client/client/transport.py
client/common/__init__.py
client/common/decorators.py
client/common/descryptors.py
client/common/errors.py
client/common/functions.py
client/common/metaclasses.py
client/common/variables.py
client/log/__init__.py
client/log/config_client_log.py
client/log/config_server_log.py
client/test/__init__.py
messenger_client.egg-info/PKG-INFO
messenger_client.egg-info/SOURCES.txt
messenger_client.egg-info/dependency_links.txt
messenger_client.egg-info/requires.txt
messenger_client.egg-info/top_level.txt