Metadata-Version: 1.0
Name: messenger-client
Version: 0.0.1
Summary: Messenger_Client
Home-page: UNKNOWN
Author: Ilia Niyazof
Author-email: mihail.pendyurin@rt.ru
License: UNKNOWN
Platform: UNKNOWN
